pyaviso/__init__.py
pyaviso/cli_aviso.py
pyaviso/cli_aviso_config.py
pyaviso/custom_exceptions.py
pyaviso/notification_manager.py
pyaviso/service_config_manager.py
pyaviso/user_config.py
pyaviso/version.py
pyaviso/authentication/__init__.py
pyaviso/authentication/auth.py
pyaviso/authentication/ecmwf_auth.py
pyaviso/authentication/etcd_auth.py
pyaviso/authentication/none_auth.py
pyaviso/authentication/openid_auth.py
pyaviso/authentication/plain_auth.py
pyaviso/engine/__init__.py
pyaviso/engine/engine.py
pyaviso/engine/engine_factory.py
pyaviso/engine/etcd_engine.py
pyaviso/engine/etcd_grpc_engine.py
pyaviso/engine/etcd_rest_engine.py
pyaviso/engine/file_based_engine.py
pyaviso/event_listeners/__init__.py
pyaviso/event_listeners/default_listener_schema.json
pyaviso/event_listeners/event_listener.py
pyaviso/event_listeners/event_listener_factory.py
pyaviso/event_listeners/listener_manager.py
pyaviso/event_listeners/listener_schema_parser.py
pyaviso/event_listeners/validation/__init__.py
pyaviso/event_listeners/validation/date_handler.py
pyaviso/event_listeners/validation/enum_handler.py
pyaviso/event_listeners/validation/float_handler.py
pyaviso/event_listeners/validation/int_handler.py
pyaviso/event_listeners/validation/regex_handler.py
pyaviso/event_listeners/validation/string_handler.py
pyaviso/event_listeners/validation/time_handler.py
pyaviso/event_listeners/validation/type_handler.py
pyaviso/triggers/__init__.py
pyaviso/triggers/command_trigger.py
pyaviso/triggers/echo_trigger.py
pyaviso/triggers/function_trigger.py
pyaviso/triggers/log_trigger.py
pyaviso/triggers/post_trigger.py
pyaviso/triggers/trigger.py
pyaviso/triggers/trigger_factory.py
pyaviso-1.0.1.dist-info/licenses/LICENSE.txt
pyaviso-1.0.1.dist-info/METADATA
pyaviso-1.0.1.dist-info/WHEEL
pyaviso-1.0.1.dist-info/entry_points.txt
pyaviso-1.0.1.dist-info/top_level.txt
pyaviso-1.0.1.dist-info/RECORD
