Metadata-Version: 2.4
Name: pyaviso
Version: 1.0.1
Summary: Time-critical notification system designed to trigger users' workflows across HPC and Cloud systems
Home-page: https://github.com/ecmwf/aviso
Author: ECMWF
Author-email: software.support@ecmwf.int
License: Apache-2.0
Classifier: Development Status :: 4 - Beta
Classifier: Intended Audience :: Developers
Classifier: Intended Audience :: Science/Research
Classifier: Natural Language :: English
Classifier: Operating System :: POSIX :: Linux
Classifier: Programming Language :: Python
Classifier: Programming Language :: Python :: 3 :: Only
Classifier: Programming Language :: Python :: 3.9
Classifier: Programming Language :: Python :: 3.10
Classifier: Programming Language :: Python :: 3.11
Classifier: Programming Language :: Python :: 3.12
License-File: LICENSE.txt
Requires-Dist: Click
Requires-Dist: etcd3>=0.11.1
Requires-Dist: PyYAML
Requires-Dist: python-json-logger
Requires-Dist: requests
Requires-Dist: parse
Requires-Dist: watchdog==2.3.1
Requires-Dist: cloudevents>=1.2.0
Requires-Dist: boto3
Requires-Dist: protobuf<=3.20.3
Dynamic: author
Dynamic: author-email
Dynamic: classifier
Dynamic: description
Dynamic: description-content-type
Dynamic: home-page
Dynamic: license
Dynamic: license-file
Dynamic: requires-dist
Dynamic: summary
